{"GlobalPropertiesHash":"vSpus8RiCMH45Ov73ZOsSWyHJCtqMcbI7UsUE/hFmUw=","FingerprintPatternsHash":"gq3WsqcKBUGTSNle7RKKyXRIwh7M8ccEqOqYvIzoM04=","PropertyOverridesHash":"8ZRc1sGeVrPBx4lD717BgRaQekyh78QKV9SKsdt638U=","InputHashes":["32/hNkwT9Qmzgjc8\u002BHmsqsAQryE/J4jr82FC4cYN4MM=","/bndLWpuwHsHm4RGiqNPJC5zCIWBAiWU8RusRLuCFZs=","HGCEzjtBOh2BHElOhF1JSZdjLYLkFWFYTMOC4Up2FbI=","2Kty/zsgzDk\u002B\u002BkvJtmX7oeap9aOhK2s\u002B6sHg2ylfddE=","ribMX\u002BfWrs/Y2LaI75eOGCSdIbD1bL4LtKBnJIT/IaU=","dt/336\u002BsbgPmvDhy4yclp2O8pI\u002Bmuo\u002Bk17D72ThF2B4=","9oVGh0S8VVUF/5T2JshnVSc0\u002BbAgIbUuCFi8fVWzDFY=","Ylz1gajZ6y7O8r\u002B7WOLaJ381fFtZkiGXtw4EF7g6LMs=","cfp27Xuse1/qRDttosJv4QWjGNCGz0GJyYvvohH4W8E=","pYT11Bon3sJkk7wFSPfY/xSzRFNefmWb6OwSnwxT7vk=","YaidOYyLhGmEzrQDqOnfTxzwKpdxLW8vjRAuuDnjsV8=","6VErtVlhjkGsjNGJ7pbe1SmKsUFTL\u002B45WlvHHiD0V50="],"CachedAssets":{"32/hNkwT9Qmzgjc8\u002BHmsqsAQryE/J4jr82FC4cYN4MM=":{"Identity":"C:\\GITHUB\\PlanningApp\\PlanningApp\\wwwroot\\app.css","SourceId":"PlanningApp","SourceType":"Discovered","ContentRoot":"C:\\GITHUB\\PlanningApp\\PlanningApp\\wwwroot\\","BasePath":"/","RelativePath":"app#[.{fingerprint}]?.css","AssetKind":"All","AssetMode":"All","AssetRole":"Primary","AssetMergeBehavior":null,"AssetMergeSource":"","RelatedAsset":null,"AssetTraitName":null,"AssetTraitValue":null,"Fingerprint":"4kywy7iv6g","Integrity":"9DR4jqepGIo9Cj7VCYKuZtZqXALX1jWq8UpnuF3uz30=","CopyToOutputDirectory":"Never","CopyToPublishDirectory":"PreserveNewest","OriginalItemSpec":"wwwroot\\app.css","FileLength":2463,"LastWriteTime":"2026-06-27T09:05:39.9034475+00:00"}},"CachedCopyCandidates":{}}